{
  "$schema": "https://ui.shadcn.com/schema/registry-item.json",
  "name": "page-studio",
  "title": "Pilates studio site (studio)",
  "description": "Calm modernist one-pager from nine studio blocks.",
  "dependencies": [
    "framer-motion",
    "lucide-react"
  ],
  "files": [
    {
      "path": "registry/blocks/layouts/page-studio.tsx",
      "content": "import { HeaderStudio } from \"@/components/blocks/header-studio\"\nimport { HeroStudio } from \"@/components/blocks/hero-studio\"\nimport { BentoStudio } from \"@/components/blocks/bento-studio\"\nimport { FeatureStudio } from \"@/components/blocks/feature-studio\"\nimport { ParallaxStudio } from \"@/components/blocks/parallax-studio\"\nimport { TestimonialsStudio } from \"@/components/blocks/testimonials-studio\"\nimport { PricingStudio } from \"@/components/blocks/pricing-studio\"\nimport { CtaStudio } from \"@/components/blocks/cta-studio\"\nimport { FooterStudio } from \"@/components/blocks/footer-studio\"\n\n/**\n * Studio Pilates page (studio vibe) — a complete one-pager pre-wired from\n * nine calm, airy blocks. Drop into a `data-vibe=\"studio\"` wrapper.\n */\nexport function PageStudio() {\n  return (\n    <main>\n      <HeaderStudio />\n      <HeroStudio />\n      <BentoStudio />\n      <FeatureStudio />\n      <ParallaxStudio />\n      <TestimonialsStudio />\n      <PricingStudio />\n      <CtaStudio />\n      <FooterStudio />\n    </main>\n  )\n}\n",
      "type": "registry:component",
      "target": "components/blocks/page-studio.tsx"
    },
    {
      "path": "registry/blocks/headers/header-studio.tsx",
      "content": "\"use client\"\n\nimport * as React from \"react\"\nimport Link from \"next/link\"\nimport { Menu, X } from \"lucide-react\"\n\nconst LINKS = [\"Classes\", \"Schedule\", \"Studio\", \"Journal\"]\n\n/**\n * Studio header — an airy serif wordmark with quiet sans nav and a blush CTA.\n */\nexport function HeaderStudio() {\n  const [open, setOpen] = React.useState(false)\n\n  return (\n    <header className=\"border-b border-border bg-background text-foreground\">\n      <div className=\"mx-auto flex max-w-6xl items-center justify-between px-6 py-5 sm:px-10\">\n        <Link href=\"#\" className=\"font-serif text-2xl tracking-tight\">\n          Méthode\n        </Link>\n\n        <nav className=\"hidden items-center gap-9 md:flex\">\n          {LINKS.map((l) => (\n            <Link key={l} href=\"#\" className=\"text-sm text-muted-foreground transition-colors hover:text-foreground\">\n              {l}\n            </Link>\n          ))}\n        </nav>\n\n        <div className=\"flex items-center gap-4\">\n          <Link\n            href=\"#\"\n            className=\"hidden rounded-full bg-primary px-6 py-2.5 text-sm font-medium text-primary-foreground transition-opacity hover:opacity-90 sm:block\"\n          >\n            Book a class\n          </Link>\n          <button onClick={() => setOpen((o) => !o)} aria-label=\"Menu\" className=\"text-foreground md:hidden\">\n            {open ? <X className=\"size-5\" /> : <Menu className=\"size-5\" />}\n          </button>\n        </div>\n      </div>\n\n      {open && (\n        <nav className=\"grid gap-1 border-t border-border px-6 py-4 md:hidden\">\n          {LINKS.map((l) => (\n            <Link key={l} href=\"#\" className=\"py-2 text-sm text-muted-foreground hover:text-foreground\">\n              {l}\n            </Link>\n          ))}\n        </nav>\n      )}\n    </header>\n  )\n}\n",
      "type": "registry:component",
      "target": "components/blocks/header-studio.tsx"
    },
    {
      "path": "registry/blocks/heroes/hero-studio.tsx",
      "content": "\"use client\"\n\nimport Link from \"next/link\"\nimport { motion } from \"framer-motion\"\nimport { ArrowRight } from \"lucide-react\"\n\nconst fadeUp = {\n  hidden: { opacity: 0, y: 20 },\n  show: { opacity: 1, y: 0, transition: { duration: 0.8, ease: [0.22, 1, 0.36, 1] as const } },\n}\n\n/**\n * Studio hero — a soft serif headline over greige with an airy media panel.\n */\nexport function HeroStudio() {\n  return (\n    <section className=\"overflow-hidden bg-background text-foreground\">\n      <div className=\"mx-auto grid max-w-6xl items-center gap-12 px-6 py-20 sm:px-10 sm:py-28 lg:grid-cols-[1.1fr_1fr]\">\n        <motion.div initial=\"hidden\" animate=\"show\" transition={{ staggerChildren: 0.12 }}>\n          <motion.p variants={fadeUp} className=\"text-xs tracking-[0.25em] uppercase text-muted-foreground\">\n            Reformer Pilates · Studio Méthode\n          </motion.p>\n          <motion.h1\n            variants={fadeUp}\n            className=\"mt-7 font-serif text-[clamp(2.75rem,7vw,5rem)] leading-[1.02] tracking-tight text-balance\"\n          >\n            Move with intention. Leave lighter.\n          </motion.h1>\n          <motion.p variants={fadeUp} className=\"mt-6 max-w-md text-lg leading-relaxed text-muted-foreground\">\n            Small classes, slow tempo, real attention. A calm place to build strength that follows\n            you off the mat.\n          </motion.p>\n          <motion.div variants={fadeUp} className=\"mt-9 flex flex-wrap items-center gap-5\">\n            <Link\n              href=\"#\"\n              className=\"inline-flex items-center gap-2 rounded-full bg-primary px-7 py-3.5 text-sm font-medium text-primary-foreground transition-opacity hover:opacity-90\"\n            >\n              Try an intro class <ArrowRight className=\"size-4\" />\n            </Link>\n            <Link href=\"#\" className=\"text-sm text-muted-foreground underline-offset-4 hover:text-foreground hover:underline\">\n              View the schedule\n            </Link>\n          </motion.div>\n        </motion.div>\n\n        <motion.div\n          initial={{ opacity: 0, scale: 0.98 }}\n          animate={{ opacity: 1, scale: 1 }}\n          transition={{ duration: 1, delay: 0.25, ease: [0.22, 1, 0.36, 1] }}\n          className=\"relative aspect-[4/5] w-full overflow-hidden rounded-[1.5rem] bg-secondary\"\n        >\n          <div className=\"absolute inset-0 bg-[radial-gradient(circle_at_30%_20%,rgba(201,142,134,0.35),transparent_60%)]\" />\n          <div className=\"absolute inset-0 bg-[radial-gradient(circle_at_80%_85%,rgba(217,194,184,0.5),transparent_55%)]\" />\n          <span className=\"absolute bottom-5 left-5 text-xs tracking-[0.2em] uppercase text-muted-foreground\">\n            No. 01 — The reformer room\n          </span>\n        </motion.div>\n      </div>\n    </section>\n  )\n}\n",
      "type": "registry:component",
      "target": "components/blocks/hero-studio.tsx"
    },
    {
      "path": "registry/blocks/bento/bento-studio.tsx",
      "content": "import { Flower2, HeartPulse, Users, Wind } from \"lucide-react\"\n\n/**\n * Studio bento — calm rounded cards in greige with a single blush accent cell.\n */\nexport function BentoStudio() {\n  return (\n    <section className=\"bg-background px-6 py-20 text-foreground sm:px-10 sm:py-28\">\n      <div className=\"mx-auto max-w-6xl\">\n        <p className=\"text-xs tracking-[0.25em] uppercase text-muted-foreground\">Why Méthode</p>\n        <h2 className=\"mt-4 max-w-2xl font-serif text-[clamp(2rem,5vw,3.5rem)] leading-[1.05] tracking-tight\">\n          A studio that moves at your pace.\n        </h2>\n\n        <div className=\"mt-12 grid auto-rows-[minmax(150px,auto)] gap-4 sm:grid-cols-3\">\n          <div className=\"flex flex-col justify-between rounded-2xl bg-primary p-7 text-primary-foreground sm:col-span-2 sm:row-span-2\">\n            <Flower2 className=\"size-8\" />\n            <div>\n              <p className=\"font-serif text-2xl\">Six to a class, never more</p>\n              <p className=\"mt-2 max-w-sm leading-relaxed text-primary-foreground/85\">\n                Every session is small enough for hands-on cues and real corrections. You are seen,\n                not herded.\n              </p>\n            </div>\n          </div>\n\n          <div className=\"flex flex-col justify-between rounded-2xl border border-border bg-card p-7\">\n            <HeartPulse className=\"size-6 text-primary\" />\n            <p className=\"font-serif text-lg\">Low-impact, all levels</p>\n          </div>\n\n          <div className=\"flex flex-col justify-between rounded-2xl border border-border bg-card p-7\">\n            <Wind className=\"size-6 text-primary\" />\n            <p className=\"font-serif text-lg\">Breath-led tempo</p>\n          </div>\n\n          <div className=\"flex items-center gap-4 rounded-2xl bg-secondary p-7 text-secondary-foreground sm:col-span-3\">\n            <Users className=\"size-7 shrink-0\" />\n            <div>\n              <p className=\"font-serif text-lg\">Teachers who remember your name</p>\n              <p className=\"leading-relaxed text-muted-foreground\">And your last session, and what your back was doing.</p>\n            </div>\n          </div>\n        </div>\n      </div>\n    </section>\n  )\n}\n",
      "type": "registry:component",
      "target": "components/blocks/bento-studio.tsx"
    },
    {
      "path": "registry/blocks/features/feature-studio.tsx",
      "content": "const ROWS = [\n  {\n    kicker: \"Strength\",\n    title: \"Build it slowly, keep it longer\",\n    body: \"Spring resistance meets controlled tempo. You leave stronger without the strain — the kind of strength that lasts past the soreness.\",\n    points: [\"Progressive loading\", \"Joint-friendly\", \"Posture-first\"],\n  },\n  {\n    kicker: \"Calm\",\n    title: \"A reset for your nervous system\",\n    body: \"Soft light, quiet rooms, breath-led movement. Most members tell us the calm is the part they can't go without.\",\n    points: [\"Breath cues throughout\", \"No mirrors, no rush\", \"Phone-free floor\"],\n  },\n]\n\n/**\n * Studio features — alternating airy rows with a soft media panel and checklist.\n */\nexport function FeatureStudio() {\n  return (\n    <section className=\"bg-background px-6 py-20 text-foreground sm:px-10 sm:py-28\">\n      <div className=\"mx-auto max-w-6xl space-y-20\">\n        {ROWS.map((r, i) => (\n          <div\n            key={r.title}\n            className={`grid items-center gap-10 lg:grid-cols-2 lg:gap-16 ${\n              i % 2 === 1 ? \"lg:[&>*:first-child]:order-2\" : \"\"\n            }`}\n          >\n            <div>\n              <p className=\"text-xs tracking-[0.25em] uppercase text-primary\">{r.kicker}</p>\n              <h3 className=\"mt-3 font-serif text-3xl leading-tight tracking-tight\">{r.title}</h3>\n              <p className=\"mt-4 leading-relaxed text-muted-foreground\">{r.body}</p>\n              <ul className=\"mt-6 space-y-3\">\n                {r.points.map((p) => (\n                  <li key={p} className=\"flex items-center gap-3 text-sm\">\n                    <span className=\"size-1.5 rounded-full bg-primary\" />\n                    {p}\n                  </li>\n                ))}\n              </ul>\n            </div>\n            <div className=\"relative aspect-[5/4] overflow-hidden rounded-[1.5rem] bg-secondary\">\n              <div className=\"absolute inset-0 bg-[radial-gradient(circle_at_50%_40%,rgba(201,142,134,0.3),transparent_60%)]\" />\n            </div>\n          </div>\n        ))}\n      </div>\n    </section>\n  )\n}\n",
      "type": "registry:component",
      "target": "components/blocks/feature-studio.tsx"
    },
    {
      "path": "registry/blocks/parallax/parallax-studio.tsx",
      "content": "\"use client\"\n\nimport { useRef } from \"react\"\nimport { motion, useScroll, useTransform } from \"framer-motion\"\n\n/**\n * Studio parallax — a calm serif statement with soft blush washes drifting on scroll.\n */\nexport function ParallaxStudio() {\n  const ref = useRef<HTMLDivElement>(null)\n  const { scrollYProgress } = useScroll({ target: ref, offset: [\"start end\", \"end start\"] })\n\n  const y1 = useTransform(scrollYProgress, [0, 1], [\"-15%\", \"15%\"])\n  const y2 = useTransform(scrollYProgress, [0, 1], [\"12%\", \"-12%\"])\n\n  return (\n    <section\n      ref={ref}\n      className=\"relative grid min-h-[440px] place-items-center overflow-hidden bg-secondary px-6 py-24 text-foreground\"\n    >\n      <motion.div\n        aria-hidden\n        style={{ y: y1 }}\n        className=\"pointer-events-none absolute -left-20 top-0 size-[28rem] rounded-full bg-[radial-gradient(circle,rgba(201,142,134,0.28),transparent_65%)]\"\n      />\n      <motion.div\n        aria-hidden\n        style={{ y: y2 }}\n        className=\"pointer-events-none absolute -right-16 bottom-0 size-[24rem] rounded-full bg-[radial-gradient(circle,rgba(217,194,184,0.5),transparent_65%)]\"\n      />\n\n      <div className=\"relative max-w-3xl text-center\">\n        <p className=\"text-xs tracking-[0.25em] uppercase text-muted-foreground\">Our philosophy</p>\n        <h2 className=\"mt-5 font-serif text-[clamp(2rem,6vw,4.25rem)] leading-[1.08] tracking-tight text-balance\">\n          Strength is quiet. So is the way we teach it.\n        </h2>\n      </div>\n    </section>\n  )\n}\n",
      "type": "registry:component",
      "target": "components/blocks/parallax-studio.tsx"
    },
    {
      "path": "registry/blocks/testimonials/testimonials-studio.tsx",
      "content": "\"use client\"\n\nimport * as React from \"react\"\nimport { ChevronLeft, ChevronRight } from \"lucide-react\"\n\nconst QUOTES = [\n  { quote: \"I came for my back and stayed for the calm. I leave every class feeling taller and quieter.\", name: \"Maya R.\", role: \"Member, 2 years\" },\n  { quote: \"The smallest classes I've ever been in. The teachers actually know my body now.\", name: \"Priya S.\", role: \"Member, 8 months\" },\n  { quote: \"Post-natal and nervous, and they made it feel safe from day one. I'm stronger than before.\", name: \"Hannah L.\", role: \"Member, 1 year\" },\n]\n\n/**\n * Studio testimonials — one soft serif quote at a time, paged with a crossfade.\n */\nexport function TestimonialsStudio() {\n  const [i, setI] = React.useState(0)\n  const q = QUOTES[i]\n\n  return (\n    <section className=\"bg-secondary px-6 py-20 text-foreground sm:px-10 sm:py-28\">\n      <div className=\"mx-auto max-w-3xl text-center\">\n        <p className=\"text-xs tracking-[0.25em] uppercase text-primary\">In their words</p>\n\n        <blockquote key={i} className=\"mt-8 font-serif text-[clamp(1.5rem,4vw,2.5rem)] leading-[1.25] tracking-tight text-balance animate-in fade-in duration-700\">\n          &ldquo;{q.quote}&rdquo;\n        </blockquote>\n\n        <p className=\"mt-7 text-sm tracking-[0.15em] uppercase text-muted-foreground\">{q.name} · {q.role}</p>\n\n        <div className=\"mt-9 flex items-center justify-center gap-4\">\n          <button\n            aria-label=\"Previous\"\n            onClick={() => setI((p) => (p - 1 + QUOTES.length) % QUOTES.length)}\n            className=\"grid size-10 place-items-center rounded-full border border-border bg-card text-muted-foreground transition-colors hover:text-foreground\"\n          >\n            <ChevronLeft className=\"size-4\" />\n          </button>\n          <span className=\"text-sm text-muted-foreground\">\n            {i + 1} / {QUOTES.length}\n          </span>\n          <button\n            aria-label=\"Next\"\n            onClick={() => setI((p) => (p + 1) % QUOTES.length)}\n            className=\"grid size-10 place-items-center rounded-full border border-border bg-card text-muted-foreground transition-colors hover:text-foreground\"\n          >\n            <ChevronRight className=\"size-4\" />\n          </button>\n        </div>\n      </div>\n    </section>\n  )\n}\n",
      "type": "registry:component",
      "target": "components/blocks/testimonials-studio.tsx"
    },
    {
      "path": "registry/blocks/pricing/pricing-studio.tsx",
      "content": "import { Check } from \"lucide-react\"\n\nconst PLANS = [\n  {\n    name: \"Intro\",\n    price: \"39\",\n    unit: \"/ 2 weeks\",\n    blurb: \"New here? Start gently.\",\n    points: [\"3 classes\", \"Any time, any class\", \"Mat loan included\"],\n    featured: false,\n  },\n  {\n    name: \"Unlimited\",\n    price: \"180\",\n    unit: \"/ month\",\n    blurb: \"For a steady practice.\",\n    points: [\"Unlimited classes\", \"Priority booking\", \"10% off the shop\", \"Guest pass monthly\"],\n    featured: true,\n  },\n  {\n    name: \"Eight pack\",\n    price: \"200\",\n    unit: \"/ 8 classes\",\n    blurb: \"Move at your own rhythm.\",\n    points: [\"8 classes, 3-month validity\", \"Shareable with a friend\", \"No commitment\"],\n    featured: false,\n  },\n]\n\n/**\n * Studio memberships — soft rounded plan cards; the featured one in blush.\n */\nexport function PricingStudio() {\n  return (\n    <section className=\"bg-background px-6 py-20 text-foreground sm:px-10 sm:py-28\">\n      <div className=\"mx-auto max-w-6xl\">\n        <div className=\"mx-auto max-w-xl text-center\">\n          <p className=\"text-xs tracking-[0.25em] uppercase text-primary\">Memberships</p>\n          <h2 className=\"mt-4 font-serif text-[clamp(2rem,5vw,3.5rem)] leading-[1.05] tracking-tight\">\n            Find your rhythm\n          </h2>\n        </div>\n\n        <div className=\"mt-12 grid items-start gap-6 md:grid-cols-3\">\n          {PLANS.map((p) => (\n            <div\n              key={p.name}\n              className={`flex flex-col rounded-[1.5rem] p-7 ${\n                p.featured ? \"bg-primary text-primary-foreground\" : \"border border-border bg-card\"\n              }`}\n            >\n              <div className=\"flex items-center justify-between\">\n                <p className=\"font-serif text-xl\">{p.name}</p>\n                {p.featured && (\n                  <span className=\"rounded-full bg-primary-foreground/15 px-3 py-0.5 text-[11px] tracking-[0.15em] uppercase\">\n                    Popular\n                  </span>\n                )}\n              </div>\n              <p className={`mt-1.5 text-sm ${p.featured ? \"text-primary-foreground/80\" : \"text-muted-foreground\"}`}>\n                {p.blurb}\n              </p>\n              <p className=\"mt-6 font-serif text-4xl tracking-tight\">\n                ${p.price}\n                <span className={`text-base ${p.featured ? \"text-primary-foreground/70\" : \"text-muted-foreground\"}`}>\n                  {\" \"}{p.unit}\n                </span>\n              </p>\n              <ul className=\"mt-6 flex-1 space-y-3\">\n                {p.points.map((pt) => (\n                  <li key={pt} className=\"flex items-start gap-3 text-sm\">\n                    <Check className={`mt-0.5 size-4 shrink-0 ${p.featured ? \"text-primary-foreground\" : \"text-primary\"}`} />\n                    {pt}\n                  </li>\n                ))}\n              </ul>\n              <button\n                className={`mt-7 rounded-full py-3 text-sm font-medium transition-opacity hover:opacity-90 ${\n                  p.featured ? \"bg-primary-foreground text-primary\" : \"bg-primary text-primary-foreground\"\n                }`}\n              >\n                Choose {p.name}\n              </button>\n            </div>\n          ))}\n        </div>\n      </div>\n    </section>\n  )\n}\n",
      "type": "registry:component",
      "target": "components/blocks/pricing-studio.tsx"
    },
    {
      "path": "registry/blocks/cta/cta-studio.tsx",
      "content": "import Link from \"next/link\"\nimport { ArrowRight } from \"lucide-react\"\n\n/**\n * Studio CTA — a calm rounded panel with a soft blush wash and one quiet action.\n */\nexport function CtaStudio() {\n  return (\n    <section className=\"bg-background px-6 py-20 text-foreground sm:px-10 sm:py-24\">\n      <div className=\"relative mx-auto max-w-5xl overflow-hidden rounded-[2rem] border border-border bg-card px-6 py-16 text-center sm:px-10 sm:py-20\">\n        <div\n          aria-hidden\n          className=\"pointer-events-none absolute inset-0 bg-[radial-gradient(circle_at_50%_120%,rgba(201,142,134,0.28),transparent_65%)]\"\n        />\n        <div className=\"relative\">\n          <p className=\"text-xs tracking-[0.25em] uppercase text-primary\">Begin where you are</p>\n          <h2 className=\"mx-auto mt-5 max-w-2xl font-serif text-[clamp(2rem,6vw,4rem)] leading-[1.05] tracking-tight\">\n            Your first class is the hardest part.\n          </h2>\n          <p className=\"mx-auto mt-5 max-w-md leading-relaxed text-muted-foreground\">\n            Three classes for $39 over two weeks. Come as you are — we&apos;ll take it from there.\n          </p>\n          <Link\n            href=\"#\"\n            className=\"mt-8 inline-flex items-center gap-2 rounded-full bg-primary px-8 py-4 text-sm font-medium text-primary-foreground transition-opacity hover:opacity-90\"\n          >\n            Start your intro <ArrowRight className=\"size-4\" />\n          </Link>\n        </div>\n      </div>\n    </section>\n  )\n}\n",
      "type": "registry:component",
      "target": "components/blocks/cta-studio.tsx"
    },
    {
      "path": "registry/blocks/footers/footer-studio.tsx",
      "content": "import Link from \"next/link\"\n\nconst COLUMNS = [\n  { title: \"Studio\", links: [\"Classes\", \"Schedule\", \"Memberships\", \"The shop\"] },\n  { title: \"About\", links: [\"The method\", \"Teachers\", \"Journal\", \"Careers\"] },\n  { title: \"Visit\", links: [\"Find us\", \"First visit\", \"Gift cards\", \"Contact\"] },\n]\n\nconst SOCIALS = [\"IG\", \"FB\", \"TT\"]\n\n/**\n * Studio footer — a calm serif wordmark over quiet hairline link columns.\n */\nexport function FooterStudio() {\n  return (\n    <footer className=\"border-t border-border bg-background px-6 py-16 text-foreground sm:px-10\">\n      <div className=\"mx-auto max-w-6xl\">\n        <div className=\"grid gap-10 border-b border-border pb-12 lg:grid-cols-[1.4fr_1fr_1fr_1fr]\">\n          <div>\n            <p className=\"font-serif text-2xl tracking-tight\">Méthode</p>\n            <p className=\"mt-4 max-w-xs leading-relaxed text-muted-foreground\">\n              A boutique reformer Pilates studio. Small classes, slow tempo, real attention.\n            </p>\n            <div className=\"mt-6 flex gap-2\">\n              {SOCIALS.map((s) => (\n                <Link\n                  key={s}\n                  href=\"#\"\n                  className=\"grid size-9 place-items-center rounded-full border border-border text-[11px] tracking-wide text-muted-foreground transition-colors hover:border-primary hover:text-foreground\"\n                >\n                  {s}\n                </Link>\n              ))}\n            </div>\n          </div>\n\n          {COLUMNS.map((col) => (\n            <div key={col.title}>\n              <p className=\"text-xs tracking-[0.2em] uppercase text-muted-foreground\">{col.title}</p>\n              <ul className=\"mt-4 space-y-2.5\">\n                {col.links.map((l) => (\n                  <li key={l}>\n                    <Link href=\"#\" className=\"text-sm text-muted-foreground transition-colors hover:text-foreground\">\n                      {l}\n                    </Link>\n                  </li>\n                ))}\n              </ul>\n            </div>\n          ))}\n        </div>\n\n        <div className=\"flex flex-col items-start justify-between gap-2 pt-6 text-xs tracking-[0.15em] uppercase text-muted-foreground sm:flex-row sm:items-center\">\n          <span>© {new Date().getFullYear()} Studio Méthode</span>\n          <span>Made to move you</span>\n        </div>\n      </div>\n    </footer>\n  )\n}\n",
      "type": "registry:component",
      "target": "components/blocks/footer-studio.tsx"
    }
  ],
  "type": "registry:block"
}