{
  "$schema": "https://ui.shadcn.com/schema/registry-item.json",
  "name": "product-brutal",
  "title": "Brutal product grid",
  "description": "Bordered product cards with a hard-shadow add button.",
  "dependencies": [
    "lucide-react"
  ],
  "files": [
    {
      "path": "registry/blocks/commerce/product-brutal.tsx",
      "content": "import { Plus } from \"lucide-react\"\n\nconst PRODUCTS = [\n  { name: \"Heavy Tee\", price: 48, tag: \"New\", swatch: \"#d9f526\" },\n  { name: \"Box Logo Cap\", price: 36, tag: null, swatch: \"#0c0c0c\" },\n  { name: \"Work Tote\", price: 28, tag: \"Restocked\", swatch: \"#e2dfd0\" },\n  { name: \"Sticker Pack\", price: 12, tag: null, swatch: \"#e11d48\" },\n  { name: \"Mono Hoodie\", price: 84, tag: \"Hot\", swatch: \"#d9f526\" },\n  { name: \"Field Notes\", price: 9, tag: null, swatch: \"#0c0c0c\" },\n]\n\n/**\n * Brutal product grid — bordered cards with a hard-shadow add button.\n */\nexport function ProductBrutal() {\n  return (\n    <section className=\"border-y-4 border-foreground bg-background px-5 py-16 text-foreground sm:px-8 sm:py-24\">\n      <div className=\"mx-auto max-w-6xl\">\n        <div className=\"flex flex-wrap items-end justify-between gap-4\">\n          <h2 className=\"text-[clamp(2rem,5vw,3.5rem)] font-black leading-[0.9] tracking-tighter uppercase\">\n            The shop.\n          </h2>\n          <p className=\"font-mono text-xs uppercase text-muted-foreground\">Free shipping over $75</p>\n        </div>\n\n        <div className=\"mt-10 grid border-2 border-foreground sm:grid-cols-2 lg:grid-cols-3\">\n          {PRODUCTS.map((p, i) => (\n            <div\n              key={p.name}\n              className=\"group border-foreground p-5 [&:not(:last-child)]:border-b-2 sm:[&:not(:nth-child(2n))]:border-r-2 sm:[&:nth-last-child(-n+2)]:border-b-0 lg:[&:not(:nth-child(3n))]:border-r-2 lg:[&:nth-last-child(-n+3)]:border-b-0\"\n            >\n              <div\n                className=\"relative aspect-square border-2 border-foreground\"\n                style={{ backgroundColor: p.swatch }}\n              >\n                {p.tag && (\n                  <span className=\"absolute top-2 left-2 border-2 border-foreground bg-background px-2 py-0.5 font-mono text-[10px] font-bold uppercase\">\n                    {p.tag}\n                  </span>\n                )}\n              </div>\n              <div className=\"mt-4 flex items-center justify-between\">\n                <div>\n                  <p className=\"text-lg font-black uppercase\">{p.name}</p>\n                  <p className=\"font-mono text-sm\">${p.price}</p>\n                </div>\n                <button\n                  aria-label={`Add ${p.name}`}\n                  className=\"grid size-11 place-items-center border-2 border-foreground bg-accent shadow-[4px_4px_0_0_var(--foreground)] transition-all hover:translate-x-[3px] hover:translate-y-[3px] hover:shadow-none\"\n                >\n                  <Plus className=\"size-5\" />\n                </button>\n              </div>\n            </div>\n          ))}\n        </div>\n      </div>\n    </section>\n  )\n}\n",
      "type": "registry:component",
      "target": "components/blocks/product-brutal.tsx"
    }
  ],
  "type": "registry:block"
}